mindvision/__init__.py
mindvision/check_param.py
mindvision/log.py
mindvision/version.py
mindvision/classification/__init__.py
mindvision/classification/dataset/__init__.py
mindvision/classification/dataset/cifar10.py
mindvision/classification/dataset/cifar100.py
mindvision/classification/dataset/fashion_mnist.py
mindvision/classification/dataset/imagenet.py
mindvision/classification/dataset/mnist.py
mindvision/classification/engine/__init__.py
mindvision/classification/engine/eval.py
mindvision/classification/engine/export.py
mindvision/classification/engine/infer.py
mindvision/classification/engine/train.py
mindvision/classification/models/__init__.py
mindvision/classification/models/builder.py
mindvision/classification/models/efficientnet.py
mindvision/classification/models/lenet.py
mindvision/classification/models/mobilenet_v2.py
mindvision/classification/models/resnet.py
mindvision/classification/models/utils.py
mindvision/classification/models/vit.py
mindvision/classification/models/backbones/__init__.py
mindvision/classification/models/backbones/efficientnet.py
mindvision/classification/models/backbones/lenet.py
mindvision/classification/models/backbones/mobilenet_v2.py
mindvision/classification/models/backbones/resnet.py
mindvision/classification/models/backbones/vit.py
mindvision/classification/models/blocks/__init__.py
mindvision/classification/models/blocks/attention.py
mindvision/classification/models/blocks/blocks.py
mindvision/classification/models/blocks/drop_path.py
mindvision/classification/models/blocks/feed_forward.py
mindvision/classification/models/blocks/patch_embedding.py
mindvision/classification/models/blocks/residual.py
mindvision/classification/models/blocks/squeeze_excite.py
mindvision/classification/models/blocks/transform.py
mindvision/classification/models/classifiers/__init__.py
mindvision/classification/models/classifiers/base.py
mindvision/classification/models/head/__init__.py
mindvision/classification/models/head/conv_head.py
mindvision-0.1.0.dist-info/LICENSE
mindvision-0.1.0.dist-info/METADATA
mindvision-0.1.0.dist-info/NOTICE
mindvision-0.1.0.dist-info/WHEEL
mindvision-0.1.0.dist-info/top_level.txt
mindvision-0.1.0.dist-info/RECORD
